.gitignore
CHANGES.txt
CONTRIBUTORS.txt
MANIFEST.in
README.rst
setup.py
docs/LICENSE.GPL
docs/LICENSE.txt
docs/MANUAL.txt
src/raptus/__init__.py
src/raptus.article.teaseme.egg-info/PKG-INFO
src/raptus.article.teaseme.egg-info/SOURCES.txt
src/raptus.article.teaseme.egg-info/dependency_links.txt
src/raptus.article.teaseme.egg-info/entry_points.txt
src/raptus.article.teaseme.egg-info/namespace_packages.txt
src/raptus.article.teaseme.egg-info/not-zip-safe
src/raptus.article.teaseme.egg-info/requires.txt
src/raptus.article.teaseme.egg-info/top_level.txt
src/raptus/article/__init__.py
src/raptus/article/teaseme/__init__.py
src/raptus/article/teaseme/configure.zcml
src/raptus/article/teaseme/setuphandlers.py
src/raptus/article/teaseme/browser/__init__.py
src/raptus/article/teaseme/browser/configure.zcml
src/raptus/article/teaseme/browser/teaseme.gif
src/raptus/article/teaseme/browser/teaseme.pt
src/raptus/article/teaseme/browser/teaseme.py
src/raptus/article/teaseme/i18n/raptus.article-de.mo
src/raptus/article/teaseme/i18n/raptus.article-de.po
src/raptus/article/teaseme/i18n/raptus.article.pot
src/raptus/article/teaseme/profiles/default/cssregistry.xml
src/raptus/article/teaseme/profiles/default/metadata.xml
src/raptus/article/teaseme/profiles/default/propertiestool.xml
src/raptus/article/teaseme/profiles/default/raptus.article.teaseme_install.txt
src/raptus/article/teaseme/profiles/default/skins.xml
src/raptus/article/teaseme/profiles/default/viewlets.xml
src/raptus/article/teaseme/skins/raptus_article_teaseme/raptus.article.teaseme.css.dtml