Metadata-Version: 1.1
Name: raptus.article.teaseme
Version: 1.0a1
Summary: Provides a responsive teaser component
Home-page: http://github.com/Raptus/raptus.article.teaseme
Author: Raptus AG
Author-email: dev@raptus.com
License: gpl
Platform: UNKNOWN
Classifier: Programming Language :: Python
